django_fast_ratelimit/__init__.py
django_fast_ratelimit/_core.py
django_fast_ratelimit/_epoch.py
django_fast_ratelimit/methods.py
django_fast_ratelimit/misc.py
django_fast_ratelimit-9.1.0.dist-info/LICENSE
django_fast_ratelimit-9.1.0.dist-info/METADATA
django_fast_ratelimit-9.1.0.dist-info/WHEEL
django_fast_ratelimit-9.1.0.dist-info/RECORD
