Metadata-Version: 2.1
Name: django-fast-ratelimit
Version: 9.1.0
Summary: Fast ratelimit implementation with django caches
Home-page: https://github.com/devkral/django-fast-ratelimit
License: MIT
Author: Alexander Kaftan
Requires-Python: >=3.9,<4.0
Classifier: Development Status :: 5 - Production/Stable
Classifier: Environment :: Web Environment
Classifier: Framework :: Django
Classifier: License :: OSI Approved :: MIT License
Classifier: Programming Language :: Python :: 3
Classifier: Programming Language :: Python :: 3.9
Classifier: Programming Language :: Python :: 3.10
Classifier: Programming Language :: Python :: 3.11
Classifier: Programming Language :: Python :: 3.12
Classifier: Programming Language :: Python :: 3 :: Only
Requires-Dist: django (>=3.0)
Project-URL: Repository, https://github.com/devkral/django-fast-ratelimit
